auth_wxwork/__init__.py
auth_wxwork/apps.py
auth_wxwork/constants.py
auth_wxwork/provider.py
auth_wxwork/views.py
sentry_wxwork/__init__.py
sentry_wxwork/plugin.py
sentry_wxwork-1.2.0.dist-info/LICENSE
sentry_wxwork-1.2.0.dist-info/METADATA
sentry_wxwork-1.2.0.dist-info/WHEEL
sentry_wxwork-1.2.0.dist-info/entry_points.txt
sentry_wxwork-1.2.0.dist-info/top_level.txt
sentry_wxwork-1.2.0.dist-info/RECORD
